{
  "groups": [
    {
      "name": "mail",
      "type": "com.itheima.reggie.common.MailProperties",
      "sourceType": "com.itheima.reggie.common.MailProperties"
    }
  ],
  "properties": [
    {
      "name": "mail.authentication",
      "type": "java.lang.String",
      "sourceType": "com.itheima.reggie.common.MailProperties"
    },
    {
      "name": "mail.smtp-port",
      "type": "java.lang.Integer",
      "sourceType": "com.itheima.reggie.common.MailProperties"
    },
    {
      "name": "mail.smtp-server",
      "type": "java.lang.String",
      "sourceType": "com.itheima.reggie.common.MailProperties"
    },
    {
      "name": "mail.suffix",
      "type": "java.lang.String",
      "sourceType": "com.itheima.reggie.common.MailProperties"
    },
    {
      "name": "mail.user",
      "type": "java.lang.String",
      "sourceType": "com.itheima.reggie.common.MailProperties"
    }
  ],
  "hints": []
}